README.rst
setup.py
flyingrhino/__init__.py
flyingrhino/utils.py
flyingrhino.egg-info/PKG-INFO
flyingrhino.egg-info/SOURCES.txt
flyingrhino.egg-info/dependency_links.txt
flyingrhino.egg-info/not-zip-safe
flyingrhino.egg-info/requires.txt
flyingrhino.egg-info/top_level.txt