Metadata-Version: 1.0
Name: flyingrhino
Version: 0.1.2
Summary: Tools for working with unmanned aerial vechicle data using python-pandas
Home-page: http://github.com/foobarbecue/flyingrhino
Author: Aaron Curtis
Author-email: aaron@aarongcurtis.com
License: Apache 2.0, see LICENCE.txt
Platform: UNKNOWN
